cca-core/__init__.py
cca-core/classification.py
cca-core/clustering.py
cca-core/concept_extraction.py
cca-core/sentiment_analysis.py
cca-core/utils.py
cca-core/lexicon_lib/MLsenticon.es.xml
cca-core/lexicon_lib/lemmatization-es.txt
cca-core/lexicon_lib/new_neg_words.txt
cca-core/lexicon_lib/new_pos_words.txt
cca_core/__init__.py
cca_core/classification.py
cca_core/clustering.py
cca_core/concept_extraction.py
cca_core/sentiment_analysis.py
cca_core/utils.py
cca_core/lexicon_lib/MLsenticon.es.xml
cca_core/lexicon_lib/lemmatization-es.txt
cca_core/lexicon_lib/new_neg_words.txt
cca_core/lexicon_lib/new_pos_words.txt
cca_core-0.1.4.dist-info/DESCRIPTION.rst
cca_core-0.1.4.dist-info/METADATA
cca_core-0.1.4.dist-info/RECORD
cca_core-0.1.4.dist-info/WHEEL
cca_core-0.1.4.dist-info/metadata.json
cca_core-0.1.4.dist-info/top_level.txt
