Metadata-Version: 2.0
Name: cca-core
Version: 0.1.4
Summary: NLP and ML modules for processing civic input
Home-page: https://github.com/ParticipaPY/cca-core
Author: Marcelo Alcaraz
Author-email: marce.mmad@gmail.com
License: UNKNOWN
Keywords: Natural Language Processing,Machine Learnign,Civic input
Platform: UNKNOWN
Requires-Python: >=3
Requires-Dist: beautifulsoup4 (>=4.6.0)
Requires-Dist: googletrans (>=2.2.0)
Requires-Dist: nltk (>=3.2.4)
Requires-Dist: pandas (>=0.20.3)
Requires-Dist: scipy
Requires-Dist: sklearn
